[
  {
    "line": 1,
    "elements": [
      {
        "line": 3,
        "name": "Payment Action",
        "description": "",
        "id": "payment-option-test;payment-action",
        "type": "scenario",
        "keyword": "Scenario",
        "steps": [
          {
            "result": {
              "duration": 37312677500,
              "status": "passed"
            },
            "line": 4,
            "name": "User on the Home page",
            "match": {
              "location": "PaymentPageSD.user_on_the_Home_page()"
            },
            "keyword": "Given "
          },
          {
            "result": {
              "duration": 27467104100,
              "status": "passed"
            },
            "line": 5,
            "name": "User clicks Cart button",
            "match": {
              "location": "PaymentPageSD.user_clicks_Cart_button()"
            },
            "keyword": "When "
          },
          {
            "result": {
              "duration": 30701449400,
              "status": "passed"
            },
            "line": 6,
            "name": "User clicks on Pay button",
            "match": {
              "location": "PaymentPageSD.user_clicks_on_Pay_button()"
            },
            "keyword": "And "
          },
          {
            "result": {
              "duration": 18333928800,
              "status": "passed"
            },
            "line": 7,
            "name": "Payment Page must be visible",
            "match": {
              "location": "PaymentPageSD.payment_Page_must_be_visible()"
            },
            "keyword": "Then "
          },
          {
            "result": {
              "duration": 3114626000,
              "status": "passed"
            },
            "line": 8,
            "name": "User clicks on the Wallets",
            "match": {
              "location": "PaymentPageSD.user_clicks_on_the_Wallets()"
            },
            "keyword": "When "
          },
          {
            "result": {
              "duration": 9418523200,
              "status": "passed"
            },
            "line": 9,
            "name": "User should be able to pay using one of the Wallets",
            "match": {
              "location": "PaymentPageSD.user_should_be_able_to_pay_using_one_of_the_Wallets()"
            },
            "keyword": "Then "
          },
          {
            "result": {
              "duration": 3142855000,
              "status": "passed"
            },
            "line": 10,
            "name": "User clicks on the Food Card",
            "match": {
              "location": "PaymentPageSD.user_clicks_on_the_Food_Card()"
            },
            "keyword": "When "
          },
          {
            "result": {
              "duration": 3124728200,
              "status": "passed"
            },
            "line": 11,
            "name": "User should be able to pay using Card",
            "match": {
              "location": "PaymentPageSD.user_should_be_able_to_pay_using_Card()"
            },
            "keyword": "Then "
          },
          {
            "result": {
              "duration": 3144420200,
              "status": "passed"
            },
            "line": 12,
            "name": "User clicks on the Credit or Debit Cards",
            "match": {
              "location": "PaymentPageSD.user_clicks_on_the_Credit_or_Debit_Cards()"
            },
            "keyword": "When "
          },
          {
            "result": {
              "duration": 3109723700,
              "status": "passed"
            },
            "line": 13,
            "name": "User Should be able to pay using Credit or Debit Cards after entering the card details",
            "match": {
              "location": "PaymentPageSD.user_Should_be_able_to_pay_using_Credit_or_Debit_Cards_after_entering_the_card_details()"
            },
            "keyword": "Then "
          },
          {
            "result": {
              "duration": 3172632700,
              "status": "passed"
            },
            "line": 14,
            "name": "User clicks on the Net Banking",
            "match": {
              "location": "PaymentPageSD.user_clicks_on_the_Net_Banking()"
            },
            "keyword": "When "
          },
          {
            "result": {
              "duration": 9329645500,
              "status": "passed"
            },
            "line": 15,
            "name": "User selects the bank by which user want to pay amount",
            "match": {
              "location": "PaymentPageSD.user_selects_the_bank_by_which_user_want_to_pay_amount()"
            },
            "keyword": "Then "
          },
          {
            "result": {
              "duration": 3150730600,
              "status": "passed"
            },
            "line": 16,
            "name": "User clicks on the more",
            "match": {
              "location": "PaymentPageSD.user_clicks_on_the_more()"
            },
            "keyword": "When "
          },
          {
            "result": {
              "duration": 7340133400,
              "status": "passed"
            },
            "line": 17,
            "name": "User clicks on the Cash On Delivery Option and will place the order",
            "match": {
              "location": "PaymentPageSD.user_clicks_on_the_Cash_On_Delivery_Option_and_will_place_the_order()"
            },
            "keyword": "Then "
          }
        ]
      }
    ],
    "name": "Payment option Test",
    "description": "",
    "id": "payment-option-test",
    "keyword": "Feature",
    "uri": "src/test/resources/Feature/Payment.feature"
  }
]